biocre/__init__.py
biocre/model.py
biocre/read.py
biocre-1.24.dist-info/licenses/LICENSE
biocre-1.24.dist-info/METADATA
biocre-1.24.dist-info/WHEEL
biocre-1.24.dist-info/top_level.txt
biocre-1.24.dist-info/RECORD
