Metadata-Version: 2.4
Name: biocre
Version: 1.24
Summary: BioCRE package
Author-email: Bingbing Xie <xie_bingbing@gzlab.ac.cn>
License: GPL-3.0-or-later
Project-URL: Home, https://github.com/xiebb7/biocre
Requires-Python: >=3.6
License-File: LICENSE
Requires-Dist: diopy
Requires-Dist: scipy
Requires-Dist: scanpy
Requires-Dist: pandas
Requires-Dist: numpy==1.23.4
Requires-Dist: natsort
Requires-Dist: matplotlib
Requires-Dist: pyranges
Requires-Dist: joblib
Requires-Dist: statsmodels
Requires-Dist: torch
Requires-Dist: tqdm
Requires-Dist: packaging
Dynamic: license-file
